pycoiler/__init__.py
pycoiler-0.1.0.dist-info/LICENSE
pycoiler-0.1.0.dist-info/METADATA
pycoiler-0.1.0.dist-info/WHEEL
pycoiler-0.1.0.dist-info/RECORD
