Metadata-Version: 2.1
Name: pycoiler
Version: 0.1.0
Summary: 
Author: Takaya Saito
Author-email: takaya.saito@outlook.com
Requires-Python: >=3.9,<4.0
Classifier: Programming Language :: Python :: 3
Classifier: Programming Language :: Python :: 3.9
Classifier: Programming Language :: Python :: 3.10
Classifier: Programming Language :: Python :: 3.11
Requires-Dist: polars (>=1.20.0,<2.0.0)
